{
    "metadata": {
        "generated_at": "2026-04-22T12:44:04.650082+00:00",
        "sources": {
            "researchers": "/home/paulossjunior/projects/horizon_project/horizon_dashboard_worspace/horizon_etl/data/exports/researchers_canonical.json",
            "initiatives": "/home/paulossjunior/projects/horizon_project/horizon_dashboard_worspace/horizon_etl/data/exports/initiatives_canonical.json",
            "research_groups": "/home/paulossjunior/projects/horizon_project/horizon_dashboard_worspace/horizon_etl/data/exports/research_groups_canonical.json",
            "advisorships": "/home/paulossjunior/projects/horizon_project/horizon_dashboard_worspace/horizon_etl/data/exports/advisorships_canonical.json"
        },
        "scope": {
            "type": "research_group",
            "research_group": {
                "id": 312,
                "name": "Química Analítica Ambiental e Aplicada",
                "short_name": null,
                "member_count": 12,
                "expanded_node_count": 12,
                "advisorship_neighbor_count": 0
            }
        },
        "weight_definition": "Each edge weight equals the total number of relationship evidences between two people. Every shared initiative, shared research group, and advisorship adds 1 to the edge weight.",
        "relation_types": {
            "initiative": "People who appear together in the same initiative team.",
            "research_group": "People who belong to the same research group.",
            "advisorship": "Supervisor and student connected by an advisorship."
        },
        "compatibility_alias": {
            "kind": "legacy_membership_graph",
            "source": "research_group_relationship_graphs/research_group_312_relationship_graph.json"
        }
    },
    "graph_stats": {
        "nodes": 12,
        "edges": 66,
        "isolated_nodes": 0,
        "connected_components": 1,
        "largest_component_size": 12,
        "relation_event_totals": {
            "initiative": 0,
            "research_group": 73,
            "advisorship": 0
        },
        "edge_relation_presence": {
            "initiative": 0,
            "research_group": 66,
            "advisorship": 0
        },
        "classification_distribution": {
            "researcher": 7,
            "student": 5
        },
        "top_people_by_weighted_degree": [
            {
                "id": 413,
                "name": "Thalles Ramon Rosa",
                "classification": "researcher",
                "weighted_degree": 15,
                "degree": 11
            },
            {
                "id": 126,
                "name": "Pedro Vitor Morbach Dixini",
                "classification": "researcher",
                "weighted_degree": 14,
                "degree": 11
            },
            {
                "id": 2671,
                "name": "Frederico da Silva Fortunato",
                "classification": "researcher",
                "weighted_degree": 14,
                "degree": 11
            },
            {
                "id": 2672,
                "name": "Jadielson Lucas da Silva Antônio",
                "classification": "researcher",
                "weighted_degree": 14,
                "degree": 11
            },
            {
                "id": 200,
                "name": "Tiago Pulce Bertelli",
                "classification": "researcher",
                "weighted_degree": 12,
                "degree": 11
            },
            {
                "id": 2842,
                "name": "Larissa Merizio de Carvalho",
                "classification": "researcher",
                "weighted_degree": 11,
                "degree": 11
            },
            {
                "id": 5694,
                "name": "Demian Paiva Alves",
                "classification": "student",
                "weighted_degree": 11,
                "degree": 11
            },
            {
                "id": 6466,
                "name": "Josiana Laporti",
                "classification": "researcher",
                "weighted_degree": 11,
                "degree": 11
            },
            {
                "id": 7537,
                "name": "Bruno Henrique Medeiros Nascimento",
                "classification": "student",
                "weighted_degree": 11,
                "degree": 11
            },
            {
                "id": 7538,
                "name": "Viviane dos Santos Marques",
                "classification": "student",
                "weighted_degree": 11,
                "degree": 11
            },
            {
                "id": 7539,
                "name": "Rayani Miranda Nunes Coser",
                "classification": "student",
                "weighted_degree": 11,
                "degree": 11
            },
            {
                "id": 7540,
                "name": "Wagner Lúcio da Silva Pacheco",
                "classification": "student",
                "weighted_degree": 11,
                "degree": 11
            }
        ]
    },
    "graph": {
        "directed": false,
        "multigraph": false,
        "graph": {},
        "nodes": [
            {
                "name": "Josiana Laporti",
                "classification": "researcher",
                "classification_confidence": "high",
                "was_student": false,
                "was_staff": true,
                "campus_name": "Aracruz",
                "degree": 11,
                "weighted_degree": 11,
                "is_group_member": true,
                "is_advisorship_neighbor": false,
                "id": 6466
            },
            {
                "name": "Tiago Pulce Bertelli",
                "classification": "researcher",
                "classification_confidence": "high",
                "was_student": false,
                "was_staff": true,
                "campus_name": "Aracruz",
                "degree": 11,
                "weighted_degree": 12,
                "is_group_member": true,
                "is_advisorship_neighbor": false,
                "id": 200
            },
            {
                "name": "Demian Paiva Alves",
                "classification": "student",
                "classification_confidence": "medium",
                "was_student": true,
                "was_staff": false,
                "campus_name": "Aracruz",
                "degree": 11,
                "weighted_degree": 11,
                "is_group_member": true,
                "is_advisorship_neighbor": false,
                "id": 5694
            },
            {
                "name": "Frederico da Silva Fortunato",
                "classification": "researcher",
                "classification_confidence": "high",
                "was_student": false,
                "was_staff": true,
                "campus_name": "Aracruz",
                "degree": 11,
                "weighted_degree": 14,
                "is_group_member": true,
                "is_advisorship_neighbor": false,
                "id": 2671
            },
            {
                "name": "Jadielson Lucas da Silva Antônio",
                "classification": "researcher",
                "classification_confidence": "high",
                "was_student": false,
                "was_staff": true,
                "campus_name": "Aracruz",
                "degree": 11,
                "weighted_degree": 14,
                "is_group_member": true,
                "is_advisorship_neighbor": false,
                "id": 2672
            },
            {
                "name": "Bruno Henrique Medeiros Nascimento",
                "classification": "student",
                "classification_confidence": "medium",
                "was_student": true,
                "was_staff": false,
                "campus_name": "Aracruz",
                "degree": 11,
                "weighted_degree": 11,
                "is_group_member": true,
                "is_advisorship_neighbor": false,
                "id": 7537
            },
            {
                "name": "Viviane dos Santos Marques",
                "classification": "student",
                "classification_confidence": "medium",
                "was_student": true,
                "was_staff": false,
                "campus_name": "Aracruz",
                "degree": 11,
                "weighted_degree": 11,
                "is_group_member": true,
                "is_advisorship_neighbor": false,
                "id": 7538
            },
            {
                "name": "Rayani Miranda Nunes Coser",
                "classification": "student",
                "classification_confidence": "medium",
                "was_student": true,
                "was_staff": false,
                "campus_name": "Aracruz",
                "degree": 11,
                "weighted_degree": 11,
                "is_group_member": true,
                "is_advisorship_neighbor": false,
                "id": 7539
            },
            {
                "name": "Wagner Lúcio da Silva Pacheco",
                "classification": "student",
                "classification_confidence": "medium",
                "was_student": true,
                "was_staff": false,
                "campus_name": "Aracruz",
                "degree": 11,
                "weighted_degree": 11,
                "is_group_member": true,
                "is_advisorship_neighbor": false,
                "id": 7540
            },
            {
                "name": "Larissa Merizio de Carvalho",
                "classification": "researcher",
                "classification_confidence": "high",
                "was_student": true,
                "was_staff": true,
                "campus_name": "Aracruz",
                "degree": 11,
                "weighted_degree": 11,
                "is_group_member": true,
                "is_advisorship_neighbor": false,
                "id": 2842
            },
            {
                "name": "Thalles Ramon Rosa",
                "classification": "researcher",
                "classification_confidence": "high",
                "was_student": false,
                "was_staff": true,
                "campus_name": "Aracruz",
                "degree": 11,
                "weighted_degree": 15,
                "is_group_member": true,
                "is_advisorship_neighbor": false,
                "id": 413
            },
            {
                "name": "Pedro Vitor Morbach Dixini",
                "classification": "researcher",
                "classification_confidence": "high",
                "was_student": false,
                "was_staff": true,
                "campus_name": "Aracruz",
                "degree": 11,
                "weighted_degree": 14,
                "is_group_member": true,
                "is_advisorship_neighbor": false,
                "id": 126
            }
        ],
        "edges": [
            {
                "weight": 1,
                "initiative_count": 0,
                "research_group_count": 1,
                "advisorship_count": 0,
                "relation_types": [
                    "research_group"
                ],
                "source": 6466,
                "target": 126
            },
            {
                "weight": 1,
                "initiative_count": 0,
                "research_group_count": 1,
                "advisorship_count": 0,
                "relation_types": [
                    "research_group"
                ],
                "source": 6466,
                "target": 200
            },
            {
                "weight": 1,
                "initiative_count": 0,
                "research_group_count": 1,
                "advisorship_count": 0,
                "relation_types": [
                    "research_group"
                ],
                "source": 6466,
                "target": 413
            },
            {
                "weight": 1,
                "initiative_count": 0,
                "research_group_count": 1,
                "advisorship_count": 0,
                "relation_types": [
                    "research_group"
                ],
                "source": 6466,
                "target": 2671
            },
            {
                "weight": 1,
                "initiative_count": 0,
                "research_group_count": 1,
                "advisorship_count": 0,
                "relation_types": [
                    "research_group"
                ],
                "source": 6466,
                "target": 2672
            },
            {
                "weight": 1,
                "initiative_count": 0,
                "research_group_count": 1,
                "advisorship_count": 0,
                "relation_types": [
                    "research_group"
                ],
                "source": 6466,
                "target": 2842
            },
            {
                "weight": 1,
                "initiative_count": 0,
                "research_group_count": 1,
                "advisorship_count": 0,
                "relation_types": [
                    "research_group"
                ],
                "source": 6466,
                "target": 5694
            },
            {
                "weight": 1,
                "initiative_count": 0,
                "research_group_count": 1,
                "advisorship_count": 0,
                "relation_types": [
                    "research_group"
                ],
                "source": 6466,
                "target": 7537
            },
            {
                "weight": 1,
                "initiative_count": 0,
                "research_group_count": 1,
                "advisorship_count": 0,
                "relation_types": [
                    "research_group"
                ],
                "source": 6466,
                "target": 7538
            },
            {
                "weight": 1,
                "initiative_count": 0,
                "research_group_count": 1,
                "advisorship_count": 0,
                "relation_types": [
                    "research_group"
                ],
                "source": 6466,
                "target": 7539
            },
            {
                "weight": 1,
                "initiative_count": 0,
                "research_group_count": 1,
                "advisorship_count": 0,
                "relation_types": [
                    "research_group"
                ],
                "source": 6466,
                "target": 7540
            },
            {
                "weight": 2,
                "initiative_count": 0,
                "research_group_count": 2,
                "advisorship_count": 0,
                "relation_types": [
                    "research_group"
                ],
                "source": 200,
                "target": 413
            },
            {
                "weight": 1,
                "initiative_count": 0,
                "research_group_count": 1,
                "advisorship_count": 0,
                "relation_types": [
                    "research_group"
                ],
                "source": 200,
                "target": 126
            },
            {
                "weight": 1,
                "initiative_count": 0,
                "research_group_count": 1,
                "advisorship_count": 0,
                "relation_types": [
                    "research_group"
                ],
                "source": 200,
                "target": 2671
            },
            {
                "weight": 1,
                "initiative_count": 0,
                "research_group_count": 1,
                "advisorship_count": 0,
                "relation_types": [
                    "research_group"
                ],
                "source": 200,
                "target": 2672
            },
            {
                "weight": 1,
                "initiative_count": 0,
                "research_group_count": 1,
                "advisorship_count": 0,
                "relation_types": [
                    "research_group"
                ],
                "source": 200,
                "target": 2842
            },
            {
                "weight": 1,
                "initiative_count": 0,
                "research_group_count": 1,
                "advisorship_count": 0,
                "relation_types": [
                    "research_group"
                ],
                "source": 200,
                "target": 5694
            },
            {
                "weight": 1,
                "initiative_count": 0,
                "research_group_count": 1,
                "advisorship_count": 0,
                "relation_types": [
                    "research_group"
                ],
                "source": 200,
                "target": 7537
            },
            {
                "weight": 1,
                "initiative_count": 0,
                "research_group_count": 1,
                "advisorship_count": 0,
                "relation_types": [
                    "research_group"
                ],
                "source": 200,
                "target": 7538
            },
            {
                "weight": 1,
                "initiative_count": 0,
                "research_group_count": 1,
                "advisorship_count": 0,
                "relation_types": [
                    "research_group"
                ],
                "source": 200,
                "target": 7539
            },
            {
                "weight": 1,
                "initiative_count": 0,
                "research_group_count": 1,
                "advisorship_count": 0,
                "relation_types": [
                    "research_group"
                ],
                "source": 200,
                "target": 7540
            },
            {
                "weight": 1,
                "initiative_count": 0,
                "research_group_count": 1,
                "advisorship_count": 0,
                "relation_types": [
                    "research_group"
                ],
                "source": 5694,
                "target": 126
            },
            {
                "weight": 1,
                "initiative_count": 0,
                "research_group_count": 1,
                "advisorship_count": 0,
                "relation_types": [
                    "research_group"
                ],
                "source": 5694,
                "target": 413
            },
            {
                "weight": 1,
                "initiative_count": 0,
                "research_group_count": 1,
                "advisorship_count": 0,
                "relation_types": [
                    "research_group"
                ],
                "source": 5694,
                "target": 2671
            },
            {
                "weight": 1,
                "initiative_count": 0,
                "research_group_count": 1,
                "advisorship_count": 0,
                "relation_types": [
                    "research_group"
                ],
                "source": 5694,
                "target": 2672
            },
            {
                "weight": 1,
                "initiative_count": 0,
                "research_group_count": 1,
                "advisorship_count": 0,
                "relation_types": [
                    "research_group"
                ],
                "source": 5694,
                "target": 2842
            },
            {
                "weight": 1,
                "initiative_count": 0,
                "research_group_count": 1,
                "advisorship_count": 0,
                "relation_types": [
                    "research_group"
                ],
                "source": 5694,
                "target": 7537
            },
            {
                "weight": 1,
                "initiative_count": 0,
                "research_group_count": 1,
                "advisorship_count": 0,
                "relation_types": [
                    "research_group"
                ],
                "source": 5694,
                "target": 7538
            },
            {
                "weight": 1,
                "initiative_count": 0,
                "research_group_count": 1,
                "advisorship_count": 0,
                "relation_types": [
                    "research_group"
                ],
                "source": 5694,
                "target": 7539
            },
            {
                "weight": 1,
                "initiative_count": 0,
                "research_group_count": 1,
                "advisorship_count": 0,
                "relation_types": [
                    "research_group"
                ],
                "source": 5694,
                "target": 7540
            },
            {
                "weight": 2,
                "initiative_count": 0,
                "research_group_count": 2,
                "advisorship_count": 0,
                "relation_types": [
                    "research_group"
                ],
                "source": 2671,
                "target": 126
            },
            {
                "weight": 2,
                "initiative_count": 0,
                "research_group_count": 2,
                "advisorship_count": 0,
                "relation_types": [
                    "research_group"
                ],
                "source": 2671,
                "target": 413
            },
            {
                "weight": 2,
                "initiative_count": 0,
                "research_group_count": 2,
                "advisorship_count": 0,
                "relation_types": [
                    "research_group"
                ],
                "source": 2671,
                "target": 2672
            },
            {
                "weight": 1,
                "initiative_count": 0,
                "research_group_count": 1,
                "advisorship_count": 0,
                "relation_types": [
                    "research_group"
                ],
                "source": 2671,
                "target": 2842
            },
            {
                "weight": 1,
                "initiative_count": 0,
                "research_group_count": 1,
                "advisorship_count": 0,
                "relation_types": [
                    "research_group"
                ],
                "source": 2671,
                "target": 7537
            },
            {
                "weight": 1,
                "initiative_count": 0,
                "research_group_count": 1,
                "advisorship_count": 0,
                "relation_types": [
                    "research_group"
                ],
                "source": 2671,
                "target": 7538
            },
            {
                "weight": 1,
                "initiative_count": 0,
                "research_group_count": 1,
                "advisorship_count": 0,
                "relation_types": [
                    "research_group"
                ],
                "source": 2671,
                "target": 7539
            },
            {
                "weight": 1,
                "initiative_count": 0,
                "research_group_count": 1,
                "advisorship_count": 0,
                "relation_types": [
                    "research_group"
                ],
                "source": 2671,
                "target": 7540
            },
            {
                "weight": 2,
                "initiative_count": 0,
                "research_group_count": 2,
                "advisorship_count": 0,
                "relation_types": [
                    "research_group"
                ],
                "source": 2672,
                "target": 126
            },
            {
                "weight": 2,
                "initiative_count": 0,
                "research_group_count": 2,
                "advisorship_count": 0,
                "relation_types": [
                    "research_group"
                ],
                "source": 2672,
                "target": 413
            },
            {
                "weight": 1,
                "initiative_count": 0,
                "research_group_count": 1,
                "advisorship_count": 0,
                "relation_types": [
                    "research_group"
                ],
                "source": 2672,
                "target": 2842
            },
            {
                "weight": 1,
                "initiative_count": 0,
                "research_group_count": 1,
                "advisorship_count": 0,
                "relation_types": [
                    "research_group"
                ],
                "source": 2672,
                "target": 7537
            },
            {
                "weight": 1,
                "initiative_count": 0,
                "research_group_count": 1,
                "advisorship_count": 0,
                "relation_types": [
                    "research_group"
                ],
                "source": 2672,
                "target": 7538
            },
            {
                "weight": 1,
                "initiative_count": 0,
                "research_group_count": 1,
                "advisorship_count": 0,
                "relation_types": [
                    "research_group"
                ],
                "source": 2672,
                "target": 7539
            },
            {
                "weight": 1,
                "initiative_count": 0,
                "research_group_count": 1,
                "advisorship_count": 0,
                "relation_types": [
                    "research_group"
                ],
                "source": 2672,
                "target": 7540
            },
            {
                "weight": 1,
                "initiative_count": 0,
                "research_group_count": 1,
                "advisorship_count": 0,
                "relation_types": [
                    "research_group"
                ],
                "source": 7537,
                "target": 126
            },
            {
                "weight": 1,
                "initiative_count": 0,
                "research_group_count": 1,
                "advisorship_count": 0,
                "relation_types": [
                    "research_group"
                ],
                "source": 7537,
                "target": 413
            },
            {
                "weight": 1,
                "initiative_count": 0,
                "research_group_count": 1,
                "advisorship_count": 0,
                "relation_types": [
                    "research_group"
                ],
                "source": 7537,
                "target": 2842
            },
            {
                "weight": 1,
                "initiative_count": 0,
                "research_group_count": 1,
                "advisorship_count": 0,
                "relation_types": [
                    "research_group"
                ],
                "source": 7537,
                "target": 7538
            },
            {
                "weight": 1,
                "initiative_count": 0,
                "research_group_count": 1,
                "advisorship_count": 0,
                "relation_types": [
                    "research_group"
                ],
                "source": 7537,
                "target": 7539
            },
            {
                "weight": 1,
                "initiative_count": 0,
                "research_group_count": 1,
                "advisorship_count": 0,
                "relation_types": [
                    "research_group"
                ],
                "source": 7537,
                "target": 7540
            },
            {
                "weight": 1,
                "initiative_count": 0,
                "research_group_count": 1,
                "advisorship_count": 0,
                "relation_types": [
                    "research_group"
                ],
                "source": 7538,
                "target": 126
            },
            {
                "weight": 1,
                "initiative_count": 0,
                "research_group_count": 1,
                "advisorship_count": 0,
                "relation_types": [
                    "research_group"
                ],
                "source": 7538,
                "target": 413
            },
            {
                "weight": 1,
                "initiative_count": 0,
                "research_group_count": 1,
                "advisorship_count": 0,
                "relation_types": [
                    "research_group"
                ],
                "source": 7538,
                "target": 2842
            },
            {
                "weight": 1,
                "initiative_count": 0,
                "research_group_count": 1,
                "advisorship_count": 0,
                "relation_types": [
                    "research_group"
                ],
                "source": 7538,
                "target": 7539
            },
            {
                "weight": 1,
                "initiative_count": 0,
                "research_group_count": 1,
                "advisorship_count": 0,
                "relation_types": [
                    "research_group"
                ],
                "source": 7538,
                "target": 7540
            },
            {
                "weight": 1,
                "initiative_count": 0,
                "research_group_count": 1,
                "advisorship_count": 0,
                "relation_types": [
                    "research_group"
                ],
                "source": 7539,
                "target": 126
            },
            {
                "weight": 1,
                "initiative_count": 0,
                "research_group_count": 1,
                "advisorship_count": 0,
                "relation_types": [
                    "research_group"
                ],
                "source": 7539,
                "target": 413
            },
            {
                "weight": 1,
                "initiative_count": 0,
                "research_group_count": 1,
                "advisorship_count": 0,
                "relation_types": [
                    "research_group"
                ],
                "source": 7539,
                "target": 2842
            },
            {
                "weight": 1,
                "initiative_count": 0,
                "research_group_count": 1,
                "advisorship_count": 0,
                "relation_types": [
                    "research_group"
                ],
                "source": 7539,
                "target": 7540
            },
            {
                "weight": 1,
                "initiative_count": 0,
                "research_group_count": 1,
                "advisorship_count": 0,
                "relation_types": [
                    "research_group"
                ],
                "source": 7540,
                "target": 126
            },
            {
                "weight": 1,
                "initiative_count": 0,
                "research_group_count": 1,
                "advisorship_count": 0,
                "relation_types": [
                    "research_group"
                ],
                "source": 7540,
                "target": 413
            },
            {
                "weight": 1,
                "initiative_count": 0,
                "research_group_count": 1,
                "advisorship_count": 0,
                "relation_types": [
                    "research_group"
                ],
                "source": 7540,
                "target": 2842
            },
            {
                "weight": 1,
                "initiative_count": 0,
                "research_group_count": 1,
                "advisorship_count": 0,
                "relation_types": [
                    "research_group"
                ],
                "source": 2842,
                "target": 126
            },
            {
                "weight": 1,
                "initiative_count": 0,
                "research_group_count": 1,
                "advisorship_count": 0,
                "relation_types": [
                    "research_group"
                ],
                "source": 2842,
                "target": 413
            },
            {
                "weight": 2,
                "initiative_count": 0,
                "research_group_count": 2,
                "advisorship_count": 0,
                "relation_types": [
                    "research_group"
                ],
                "source": 413,
                "target": 126
            }
        ]
    }
}