{
    "metadata": {
        "generated_at": "2026-04-22T12:44:00.130431+00:00",
        "sources": {
            "researchers": "/home/paulossjunior/projects/horizon_project/horizon_dashboard_worspace/horizon_etl/data/exports/researchers_canonical.json",
            "initiatives": "/home/paulossjunior/projects/horizon_project/horizon_dashboard_worspace/horizon_etl/data/exports/initiatives_canonical.json",
            "research_groups": "/home/paulossjunior/projects/horizon_project/horizon_dashboard_worspace/horizon_etl/data/exports/research_groups_canonical.json",
            "advisorships": "/home/paulossjunior/projects/horizon_project/horizon_dashboard_worspace/horizon_etl/data/exports/advisorships_canonical.json"
        },
        "scope": {
            "type": "research_group",
            "research_group": {
                "id": 171,
                "name": "Grupo de Pesquisa em Física Experimental (GPFE - IFES)",
                "short_name": "GPFE - IFES",
                "member_count": 19,
                "expanded_node_count": 20,
                "advisorship_neighbor_count": 1
            }
        },
        "weight_definition": "Each edge weight equals the total number of relationship evidences between two people. Every shared initiative, shared research group, and advisorship adds 1 to the edge weight.",
        "relation_types": {
            "initiative": "People who appear together in the same initiative team.",
            "research_group": "People who belong to the same research group.",
            "advisorship": "Supervisor and student connected by an advisorship."
        }
    },
    "graph_stats": {
        "nodes": 20,
        "edges": 172,
        "isolated_nodes": 0,
        "connected_components": 1,
        "largest_component_size": 20,
        "relation_event_totals": {
            "initiative": 1,
            "research_group": 195,
            "advisorship": 1
        },
        "edge_relation_presence": {
            "initiative": 1,
            "research_group": 171,
            "advisorship": 1
        },
        "classification_distribution": {
            "researcher": 7,
            "student": 13
        },
        "top_people_by_weighted_degree": [
            {
                "id": 5272,
                "name": "Alexandre Barbosa de Souza",
                "classification": "researcher",
                "weighted_degree": 26,
                "degree": 19
            },
            {
                "id": 238,
                "name": "Emmanuela Melo De Andrade Sternberg",
                "classification": "researcher",
                "weighted_degree": 24,
                "degree": 18
            },
            {
                "id": 240,
                "name": "Filipe Leôncio Braga",
                "classification": "researcher",
                "weighted_degree": 24,
                "degree": 18
            },
            {
                "id": 5265,
                "name": "Soraia Cristina Gonzaga Neves Braga",
                "classification": "researcher",
                "weighted_degree": 24,
                "degree": 18
            },
            {
                "id": 5270,
                "name": "Maria Alice Ribeiro Dias",
                "classification": "student",
                "weighted_degree": 24,
                "degree": 18
            },
            {
                "id": 5275,
                "name": "Hezylei José Joaquim Francischetto Avelino",
                "classification": "student",
                "weighted_degree": 24,
                "degree": 18
            },
            {
                "id": 5278,
                "name": "Telmo Paes Barreto Junior",
                "classification": "student",
                "weighted_degree": 24,
                "degree": 18
            },
            {
                "id": 5267,
                "name": "Diego de Oliveira Pezzin",
                "classification": "student",
                "weighted_degree": 20,
                "degree": 18
            },
            {
                "id": 5268,
                "name": "Gabriel da Costa Galeano",
                "classification": "student",
                "weighted_degree": 20,
                "degree": 18
            },
            {
                "id": 5274,
                "name": "Felipe Tófolo de Siqueira Penha",
                "classification": "student",
                "weighted_degree": 20,
                "degree": 18
            },
            {
                "id": 5263,
                "name": "Elias Vergílio da Cas",
                "classification": "researcher",
                "weighted_degree": 18,
                "degree": 18
            },
            {
                "id": 5264,
                "name": "Nicolau Andre Silveira Rodrigues",
                "classification": "researcher",
                "weighted_degree": 18,
                "degree": 18
            },
            {
                "id": 5266,
                "name": "David Gomes Figueiredo",
                "classification": "student",
                "weighted_degree": 18,
                "degree": 18
            },
            {
                "id": 5269,
                "name": "José Renato Vidigal Filho",
                "classification": "student",
                "weighted_degree": 18,
                "degree": 18
            },
            {
                "id": 5271,
                "name": "Thaizy Carlos Nossa",
                "classification": "student",
                "weighted_degree": 18,
                "degree": 18
            },
            {
                "id": 5273,
                "name": "Ana Clara Sena Prates",
                "classification": "student",
                "weighted_degree": 18,
                "degree": 18
            },
            {
                "id": 5276,
                "name": "Lucas Figueiredo Matos",
                "classification": "student",
                "weighted_degree": 18,
                "degree": 18
            },
            {
                "id": 5277,
                "name": "Rodrigo Lopes Alvarino",
                "classification": "student",
                "weighted_degree": 18,
                "degree": 18
            },
            {
                "id": 5279,
                "name": "William Henrique Silva Profeta",
                "classification": "student",
                "weighted_degree": 18,
                "degree": 18
            },
            {
                "id": 127,
                "name": "Flavio Barcelos Braz Da Silva",
                "classification": "researcher",
                "weighted_degree": 2,
                "degree": 1
            }
        ]
    },
    "graph": {
        "directed": false,
        "multigraph": false,
        "graph": {},
        "nodes": [
            {
                "name": "Elias Vergílio da Cas",
                "classification": "researcher",
                "classification_confidence": "high",
                "was_student": false,
                "was_staff": true,
                "campus_name": "Cariacica",
                "degree": 18,
                "weighted_degree": 18,
                "is_group_member": true,
                "is_advisorship_neighbor": false,
                "id": 5263
            },
            {
                "name": "Nicolau Andre Silveira Rodrigues",
                "classification": "researcher",
                "classification_confidence": "high",
                "was_student": false,
                "was_staff": true,
                "campus_name": "Cariacica",
                "degree": 18,
                "weighted_degree": 18,
                "is_group_member": true,
                "is_advisorship_neighbor": false,
                "id": 5264
            },
            {
                "name": "Soraia Cristina Gonzaga Neves Braga",
                "classification": "researcher",
                "classification_confidence": "high",
                "was_student": false,
                "was_staff": true,
                "campus_name": "Cariacica",
                "degree": 18,
                "weighted_degree": 24,
                "is_group_member": true,
                "is_advisorship_neighbor": false,
                "id": 5265
            },
            {
                "name": "David Gomes Figueiredo",
                "classification": "student",
                "classification_confidence": "medium",
                "was_student": true,
                "was_staff": false,
                "campus_name": "Cariacica",
                "degree": 18,
                "weighted_degree": 18,
                "is_group_member": true,
                "is_advisorship_neighbor": false,
                "id": 5266
            },
            {
                "name": "Diego de Oliveira Pezzin",
                "classification": "student",
                "classification_confidence": "medium",
                "was_student": true,
                "was_staff": false,
                "campus_name": "Cariacica",
                "degree": 18,
                "weighted_degree": 20,
                "is_group_member": true,
                "is_advisorship_neighbor": false,
                "id": 5267
            },
            {
                "name": "Gabriel da Costa Galeano",
                "classification": "student",
                "classification_confidence": "medium",
                "was_student": true,
                "was_staff": false,
                "campus_name": "Cariacica",
                "degree": 18,
                "weighted_degree": 20,
                "is_group_member": true,
                "is_advisorship_neighbor": false,
                "id": 5268
            },
            {
                "name": "José Renato Vidigal Filho",
                "classification": "student",
                "classification_confidence": "medium",
                "was_student": true,
                "was_staff": false,
                "campus_name": "Cariacica",
                "degree": 18,
                "weighted_degree": 18,
                "is_group_member": true,
                "is_advisorship_neighbor": false,
                "id": 5269
            },
            {
                "name": "Maria Alice Ribeiro Dias",
                "classification": "student",
                "classification_confidence": "medium",
                "was_student": true,
                "was_staff": false,
                "campus_name": "Cariacica",
                "degree": 18,
                "weighted_degree": 24,
                "is_group_member": true,
                "is_advisorship_neighbor": false,
                "id": 5270
            },
            {
                "name": "Thaizy Carlos Nossa",
                "classification": "student",
                "classification_confidence": "medium",
                "was_student": true,
                "was_staff": false,
                "campus_name": "Cariacica",
                "degree": 18,
                "weighted_degree": 18,
                "is_group_member": true,
                "is_advisorship_neighbor": false,
                "id": 5271
            },
            {
                "name": "Alexandre Barbosa de Souza",
                "classification": "researcher",
                "classification_confidence": "high",
                "was_student": true,
                "was_staff": true,
                "campus_name": "Cariacica",
                "degree": 19,
                "weighted_degree": 26,
                "is_group_member": true,
                "is_advisorship_neighbor": false,
                "id": 5272
            },
            {
                "name": "Ana Clara Sena Prates",
                "classification": "student",
                "classification_confidence": "medium",
                "was_student": true,
                "was_staff": false,
                "campus_name": "Cariacica",
                "degree": 18,
                "weighted_degree": 18,
                "is_group_member": true,
                "is_advisorship_neighbor": false,
                "id": 5273
            },
            {
                "name": "Felipe Tófolo de Siqueira Penha",
                "classification": "student",
                "classification_confidence": "medium",
                "was_student": true,
                "was_staff": false,
                "campus_name": "Cariacica",
                "degree": 18,
                "weighted_degree": 20,
                "is_group_member": true,
                "is_advisorship_neighbor": false,
                "id": 5274
            },
            {
                "name": "Hezylei José Joaquim Francischetto Avelino",
                "classification": "student",
                "classification_confidence": "medium",
                "was_student": true,
                "was_staff": false,
                "campus_name": "Cariacica",
                "degree": 18,
                "weighted_degree": 24,
                "is_group_member": true,
                "is_advisorship_neighbor": false,
                "id": 5275
            },
            {
                "name": "Lucas Figueiredo Matos",
                "classification": "student",
                "classification_confidence": "medium",
                "was_student": true,
                "was_staff": false,
                "campus_name": "Cariacica",
                "degree": 18,
                "weighted_degree": 18,
                "is_group_member": true,
                "is_advisorship_neighbor": false,
                "id": 5276
            },
            {
                "name": "Rodrigo Lopes Alvarino",
                "classification": "student",
                "classification_confidence": "medium",
                "was_student": true,
                "was_staff": false,
                "campus_name": "Cariacica",
                "degree": 18,
                "weighted_degree": 18,
                "is_group_member": true,
                "is_advisorship_neighbor": false,
                "id": 5277
            },
            {
                "name": "Telmo Paes Barreto Junior",
                "classification": "student",
                "classification_confidence": "medium",
                "was_student": true,
                "was_staff": false,
                "campus_name": "Cariacica",
                "degree": 18,
                "weighted_degree": 24,
                "is_group_member": true,
                "is_advisorship_neighbor": false,
                "id": 5278
            },
            {
                "name": "William Henrique Silva Profeta",
                "classification": "student",
                "classification_confidence": "medium",
                "was_student": true,
                "was_staff": false,
                "campus_name": "Cariacica",
                "degree": 18,
                "weighted_degree": 18,
                "is_group_member": true,
                "is_advisorship_neighbor": false,
                "id": 5279
            },
            {
                "name": "Emmanuela Melo De Andrade Sternberg",
                "classification": "researcher",
                "classification_confidence": "high",
                "was_student": false,
                "was_staff": true,
                "campus_name": "Cariacica",
                "degree": 18,
                "weighted_degree": 24,
                "is_group_member": true,
                "is_advisorship_neighbor": false,
                "id": 238
            },
            {
                "name": "Filipe Leôncio Braga",
                "classification": "researcher",
                "classification_confidence": "high",
                "was_student": false,
                "was_staff": true,
                "campus_name": "Cariacica",
                "degree": 18,
                "weighted_degree": 24,
                "is_group_member": true,
                "is_advisorship_neighbor": false,
                "id": 240
            },
            {
                "name": "Flavio Barcelos Braz Da Silva",
                "classification": "researcher",
                "classification_confidence": "high",
                "was_student": false,
                "was_staff": true,
                "campus_name": "Serra",
                "degree": 1,
                "weighted_degree": 2,
                "is_group_member": false,
                "is_advisorship_neighbor": true,
                "id": 127
            }
        ],
        "edges": [
            {
                "weight": 1,
                "initiative_count": 0,
                "research_group_count": 1,
                "advisorship_count": 0,
                "relation_types": [
                    "research_group"
                ],
                "source": 5263,
                "target": 238
            },
            {
                "weight": 1,
                "initiative_count": 0,
                "research_group_count": 1,
                "advisorship_count": 0,
                "relation_types": [
                    "research_group"
                ],
                "source": 5263,
                "target": 240
            },
            {
                "weight": 1,
                "initiative_count": 0,
                "research_group_count": 1,
                "advisorship_count": 0,
                "relation_types": [
                    "research_group"
                ],
                "source": 5263,
                "target": 5264
            },
            {
                "weight": 1,
                "initiative_count": 0,
                "research_group_count": 1,
                "advisorship_count": 0,
                "relation_types": [
                    "research_group"
                ],
                "source": 5263,
                "target": 5265
            },
            {
                "weight": 1,
                "initiative_count": 0,
                "research_group_count": 1,
                "advisorship_count": 0,
                "relation_types": [
                    "research_group"
                ],
                "source": 5263,
                "target": 5266
            },
            {
                "weight": 1,
                "initiative_count": 0,
                "research_group_count": 1,
                "advisorship_count": 0,
                "relation_types": [
                    "research_group"
                ],
                "source": 5263,
                "target": 5267
            },
            {
                "weight": 1,
                "initiative_count": 0,
                "research_group_count": 1,
                "advisorship_count": 0,
                "relation_types": [
                    "research_group"
                ],
                "source": 5263,
                "target": 5268
            },
            {
                "weight": 1,
                "initiative_count": 0,
                "research_group_count": 1,
                "advisorship_count": 0,
                "relation_types": [
                    "research_group"
                ],
                "source": 5263,
                "target": 5269
            },
            {
                "weight": 1,
                "initiative_count": 0,
                "research_group_count": 1,
                "advisorship_count": 0,
                "relation_types": [
                    "research_group"
                ],
                "source": 5263,
                "target": 5270
            },
            {
                "weight": 1,
                "initiative_count": 0,
                "research_group_count": 1,
                "advisorship_count": 0,
                "relation_types": [
                    "research_group"
                ],
                "source": 5263,
                "target": 5271
            },
            {
                "weight": 1,
                "initiative_count": 0,
                "research_group_count": 1,
                "advisorship_count": 0,
                "relation_types": [
                    "research_group"
                ],
                "source": 5263,
                "target": 5272
            },
            {
                "weight": 1,
                "initiative_count": 0,
                "research_group_count": 1,
                "advisorship_count": 0,
                "relation_types": [
                    "research_group"
                ],
                "source": 5263,
                "target": 5273
            },
            {
                "weight": 1,
                "initiative_count": 0,
                "research_group_count": 1,
                "advisorship_count": 0,
                "relation_types": [
                    "research_group"
                ],
                "source": 5263,
                "target": 5274
            },
            {
                "weight": 1,
                "initiative_count": 0,
                "research_group_count": 1,
                "advisorship_count": 0,
                "relation_types": [
                    "research_group"
                ],
                "source": 5263,
                "target": 5275
            },
            {
                "weight": 1,
                "initiative_count": 0,
                "research_group_count": 1,
                "advisorship_count": 0,
                "relation_types": [
                    "research_group"
                ],
                "source": 5263,
                "target": 5276
            },
            {
                "weight": 1,
                "initiative_count": 0,
                "research_group_count": 1,
                "advisorship_count": 0,
                "relation_types": [
                    "research_group"
                ],
                "source": 5263,
                "target": 5277
            },
            {
                "weight": 1,
                "initiative_count": 0,
                "research_group_count": 1,
                "advisorship_count": 0,
                "relation_types": [
                    "research_group"
                ],
                "source": 5263,
                "target": 5278
            },
            {
                "weight": 1,
                "initiative_count": 0,
                "research_group_count": 1,
                "advisorship_count": 0,
                "relation_types": [
                    "research_group"
                ],
                "source": 5263,
                "target": 5279
            },
            {
                "weight": 1,
                "initiative_count": 0,
                "research_group_count": 1,
                "advisorship_count": 0,
                "relation_types": [
                    "research_group"
                ],
                "source": 5264,
                "target": 238
            },
            {
                "weight": 1,
                "initiative_count": 0,
                "research_group_count": 1,
                "advisorship_count": 0,
                "relation_types": [
                    "research_group"
                ],
                "source": 5264,
                "target": 240
            },
            {
                "weight": 1,
                "initiative_count": 0,
                "research_group_count": 1,
                "advisorship_count": 0,
                "relation_types": [
                    "research_group"
                ],
                "source": 5264,
                "target": 5265
            },
            {
                "weight": 1,
                "initiative_count": 0,
                "research_group_count": 1,
                "advisorship_count": 0,
                "relation_types": [
                    "research_group"
                ],
                "source": 5264,
                "target": 5266
            },
            {
                "weight": 1,
                "initiative_count": 0,
                "research_group_count": 1,
                "advisorship_count": 0,
                "relation_types": [
                    "research_group"
                ],
                "source": 5264,
                "target": 5267
            },
            {
                "weight": 1,
                "initiative_count": 0,
                "research_group_count": 1,
                "advisorship_count": 0,
                "relation_types": [
                    "research_group"
                ],
                "source": 5264,
                "target": 5268
            },
            {
                "weight": 1,
                "initiative_count": 0,
                "research_group_count": 1,
                "advisorship_count": 0,
                "relation_types": [
                    "research_group"
                ],
                "source": 5264,
                "target": 5269
            },
            {
                "weight": 1,
                "initiative_count": 0,
                "research_group_count": 1,
                "advisorship_count": 0,
                "relation_types": [
                    "research_group"
                ],
                "source": 5264,
                "target": 5270
            },
            {
                "weight": 1,
                "initiative_count": 0,
                "research_group_count": 1,
                "advisorship_count": 0,
                "relation_types": [
                    "research_group"
                ],
                "source": 5264,
                "target": 5271
            },
            {
                "weight": 1,
                "initiative_count": 0,
                "research_group_count": 1,
                "advisorship_count": 0,
                "relation_types": [
                    "research_group"
                ],
                "source": 5264,
                "target": 5272
            },
            {
                "weight": 1,
                "initiative_count": 0,
                "research_group_count": 1,
                "advisorship_count": 0,
                "relation_types": [
                    "research_group"
                ],
                "source": 5264,
                "target": 5273
            },
            {
                "weight": 1,
                "initiative_count": 0,
                "research_group_count": 1,
                "advisorship_count": 0,
                "relation_types": [
                    "research_group"
                ],
                "source": 5264,
                "target": 5274
            },
            {
                "weight": 1,
                "initiative_count": 0,
                "research_group_count": 1,
                "advisorship_count": 0,
                "relation_types": [
                    "research_group"
                ],
                "source": 5264,
                "target": 5275
            },
            {
                "weight": 1,
                "initiative_count": 0,
                "research_group_count": 1,
                "advisorship_count": 0,
                "relation_types": [
                    "research_group"
                ],
                "source": 5264,
                "target": 5276
            },
            {
                "weight": 1,
                "initiative_count": 0,
                "research_group_count": 1,
                "advisorship_count": 0,
                "relation_types": [
                    "research_group"
                ],
                "source": 5264,
                "target": 5277
            },
            {
                "weight": 1,
                "initiative_count": 0,
                "research_group_count": 1,
                "advisorship_count": 0,
                "relation_types": [
                    "research_group"
                ],
                "source": 5264,
                "target": 5278
            },
            {
                "weight": 1,
                "initiative_count": 0,
                "research_group_count": 1,
                "advisorship_count": 0,
                "relation_types": [
                    "research_group"
                ],
                "source": 5264,
                "target": 5279
            },
            {
                "weight": 2,
                "initiative_count": 0,
                "research_group_count": 2,
                "advisorship_count": 0,
                "relation_types": [
                    "research_group"
                ],
                "source": 5265,
                "target": 238
            },
            {
                "weight": 2,
                "initiative_count": 0,
                "research_group_count": 2,
                "advisorship_count": 0,
                "relation_types": [
                    "research_group"
                ],
                "source": 5265,
                "target": 240
            },
            {
                "weight": 1,
                "initiative_count": 0,
                "research_group_count": 1,
                "advisorship_count": 0,
                "relation_types": [
                    "research_group"
                ],
                "source": 5265,
                "target": 5266
            },
            {
                "weight": 1,
                "initiative_count": 0,
                "research_group_count": 1,
                "advisorship_count": 0,
                "relation_types": [
                    "research_group"
                ],
                "source": 5265,
                "target": 5267
            },
            {
                "weight": 1,
                "initiative_count": 0,
                "research_group_count": 1,
                "advisorship_count": 0,
                "relation_types": [
                    "research_group"
                ],
                "source": 5265,
                "target": 5268
            },
            {
                "weight": 1,
                "initiative_count": 0,
                "research_group_count": 1,
                "advisorship_count": 0,
                "relation_types": [
                    "research_group"
                ],
                "source": 5265,
                "target": 5269
            },
            {
                "weight": 2,
                "initiative_count": 0,
                "research_group_count": 2,
                "advisorship_count": 0,
                "relation_types": [
                    "research_group"
                ],
                "source": 5265,
                "target": 5270
            },
            {
                "weight": 1,
                "initiative_count": 0,
                "research_group_count": 1,
                "advisorship_count": 0,
                "relation_types": [
                    "research_group"
                ],
                "source": 5265,
                "target": 5271
            },
            {
                "weight": 2,
                "initiative_count": 0,
                "research_group_count": 2,
                "advisorship_count": 0,
                "relation_types": [
                    "research_group"
                ],
                "source": 5265,
                "target": 5272
            },
            {
                "weight": 1,
                "initiative_count": 0,
                "research_group_count": 1,
                "advisorship_count": 0,
                "relation_types": [
                    "research_group"
                ],
                "source": 5265,
                "target": 5273
            },
            {
                "weight": 1,
                "initiative_count": 0,
                "research_group_count": 1,
                "advisorship_count": 0,
                "relation_types": [
                    "research_group"
                ],
                "source": 5265,
                "target": 5274
            },
            {
                "weight": 2,
                "initiative_count": 0,
                "research_group_count": 2,
                "advisorship_count": 0,
                "relation_types": [
                    "research_group"
                ],
                "source": 5265,
                "target": 5275
            },
            {
                "weight": 1,
                "initiative_count": 0,
                "research_group_count": 1,
                "advisorship_count": 0,
                "relation_types": [
                    "research_group"
                ],
                "source": 5265,
                "target": 5276
            },
            {
                "weight": 1,
                "initiative_count": 0,
                "research_group_count": 1,
                "advisorship_count": 0,
                "relation_types": [
                    "research_group"
                ],
                "source": 5265,
                "target": 5277
            },
            {
                "weight": 2,
                "initiative_count": 0,
                "research_group_count": 2,
                "advisorship_count": 0,
                "relation_types": [
                    "research_group"
                ],
                "source": 5265,
                "target": 5278
            },
            {
                "weight": 1,
                "initiative_count": 0,
                "research_group_count": 1,
                "advisorship_count": 0,
                "relation_types": [
                    "research_group"
                ],
                "source": 5265,
                "target": 5279
            },
            {
                "weight": 1,
                "initiative_count": 0,
                "research_group_count": 1,
                "advisorship_count": 0,
                "relation_types": [
                    "research_group"
                ],
                "source": 5266,
                "target": 238
            },
            {
                "weight": 1,
                "initiative_count": 0,
                "research_group_count": 1,
                "advisorship_count": 0,
                "relation_types": [
                    "research_group"
                ],
                "source": 5266,
                "target": 240
            },
            {
                "weight": 1,
                "initiative_count": 0,
                "research_group_count": 1,
                "advisorship_count": 0,
                "relation_types": [
                    "research_group"
                ],
                "source": 5266,
                "target": 5267
            },
            {
                "weight": 1,
                "initiative_count": 0,
                "research_group_count": 1,
                "advisorship_count": 0,
                "relation_types": [
                    "research_group"
                ],
                "source": 5266,
                "target": 5268
            },
            {
                "weight": 1,
                "initiative_count": 0,
                "research_group_count": 1,
                "advisorship_count": 0,
                "relation_types": [
                    "research_group"
                ],
                "source": 5266,
                "target": 5269
            },
            {
                "weight": 1,
                "initiative_count": 0,
                "research_group_count": 1,
                "advisorship_count": 0,
                "relation_types": [
                    "research_group"
                ],
                "source": 5266,
                "target": 5270
            },
            {
                "weight": 1,
                "initiative_count": 0,
                "research_group_count": 1,
                "advisorship_count": 0,
                "relation_types": [
                    "research_group"
                ],
                "source": 5266,
                "target": 5271
            },
            {
                "weight": 1,
                "initiative_count": 0,
                "research_group_count": 1,
                "advisorship_count": 0,
                "relation_types": [
                    "research_group"
                ],
                "source": 5266,
                "target": 5272
            },
            {
                "weight": 1,
                "initiative_count": 0,
                "research_group_count": 1,
                "advisorship_count": 0,
                "relation_types": [
                    "research_group"
                ],
                "source": 5266,
                "target": 5273
            },
            {
                "weight": 1,
                "initiative_count": 0,
                "research_group_count": 1,
                "advisorship_count": 0,
                "relation_types": [
                    "research_group"
                ],
                "source": 5266,
                "target": 5274
            },
            {
                "weight": 1,
                "initiative_count": 0,
                "research_group_count": 1,
                "advisorship_count": 0,
                "relation_types": [
                    "research_group"
                ],
                "source": 5266,
                "target": 5275
            },
            {
                "weight": 1,
                "initiative_count": 0,
                "research_group_count": 1,
                "advisorship_count": 0,
                "relation_types": [
                    "research_group"
                ],
                "source": 5266,
                "target": 5276
            },
            {
                "weight": 1,
                "initiative_count": 0,
                "research_group_count": 1,
                "advisorship_count": 0,
                "relation_types": [
                    "research_group"
                ],
                "source": 5266,
                "target": 5277
            },
            {
                "weight": 1,
                "initiative_count": 0,
                "research_group_count": 1,
                "advisorship_count": 0,
                "relation_types": [
                    "research_group"
                ],
                "source": 5266,
                "target": 5278
            },
            {
                "weight": 1,
                "initiative_count": 0,
                "research_group_count": 1,
                "advisorship_count": 0,
                "relation_types": [
                    "research_group"
                ],
                "source": 5266,
                "target": 5279
            },
            {
                "weight": 1,
                "initiative_count": 0,
                "research_group_count": 1,
                "advisorship_count": 0,
                "relation_types": [
                    "research_group"
                ],
                "source": 5267,
                "target": 238
            },
            {
                "weight": 1,
                "initiative_count": 0,
                "research_group_count": 1,
                "advisorship_count": 0,
                "relation_types": [
                    "research_group"
                ],
                "source": 5267,
                "target": 240
            },
            {
                "weight": 2,
                "initiative_count": 0,
                "research_group_count": 2,
                "advisorship_count": 0,
                "relation_types": [
                    "research_group"
                ],
                "source": 5267,
                "target": 5268
            },
            {
                "weight": 1,
                "initiative_count": 0,
                "research_group_count": 1,
                "advisorship_count": 0,
                "relation_types": [
                    "research_group"
                ],
                "source": 5267,
                "target": 5269
            },
            {
                "weight": 1,
                "initiative_count": 0,
                "research_group_count": 1,
                "advisorship_count": 0,
                "relation_types": [
                    "research_group"
                ],
                "source": 5267,
                "target": 5270
            },
            {
                "weight": 1,
                "initiative_count": 0,
                "research_group_count": 1,
                "advisorship_count": 0,
                "relation_types": [
                    "research_group"
                ],
                "source": 5267,
                "target": 5271
            },
            {
                "weight": 1,
                "initiative_count": 0,
                "research_group_count": 1,
                "advisorship_count": 0,
                "relation_types": [
                    "research_group"
                ],
                "source": 5267,
                "target": 5272
            },
            {
                "weight": 1,
                "initiative_count": 0,
                "research_group_count": 1,
                "advisorship_count": 0,
                "relation_types": [
                    "research_group"
                ],
                "source": 5267,
                "target": 5273
            },
            {
                "weight": 2,
                "initiative_count": 0,
                "research_group_count": 2,
                "advisorship_count": 0,
                "relation_types": [
                    "research_group"
                ],
                "source": 5267,
                "target": 5274
            },
            {
                "weight": 1,
                "initiative_count": 0,
                "research_group_count": 1,
                "advisorship_count": 0,
                "relation_types": [
                    "research_group"
                ],
                "source": 5267,
                "target": 5275
            },
            {
                "weight": 1,
                "initiative_count": 0,
                "research_group_count": 1,
                "advisorship_count": 0,
                "relation_types": [
                    "research_group"
                ],
                "source": 5267,
                "target": 5276
            },
            {
                "weight": 1,
                "initiative_count": 0,
                "research_group_count": 1,
                "advisorship_count": 0,
                "relation_types": [
                    "research_group"
                ],
                "source": 5267,
                "target": 5277
            },
            {
                "weight": 1,
                "initiative_count": 0,
                "research_group_count": 1,
                "advisorship_count": 0,
                "relation_types": [
                    "research_group"
                ],
                "source": 5267,
                "target": 5278
            },
            {
                "weight": 1,
                "initiative_count": 0,
                "research_group_count": 1,
                "advisorship_count": 0,
                "relation_types": [
                    "research_group"
                ],
                "source": 5267,
                "target": 5279
            },
            {
                "weight": 1,
                "initiative_count": 0,
                "research_group_count": 1,
                "advisorship_count": 0,
                "relation_types": [
                    "research_group"
                ],
                "source": 5268,
                "target": 238
            },
            {
                "weight": 1,
                "initiative_count": 0,
                "research_group_count": 1,
                "advisorship_count": 0,
                "relation_types": [
                    "research_group"
                ],
                "source": 5268,
                "target": 240
            },
            {
                "weight": 1,
                "initiative_count": 0,
                "research_group_count": 1,
                "advisorship_count": 0,
                "relation_types": [
                    "research_group"
                ],
                "source": 5268,
                "target": 5269
            },
            {
                "weight": 1,
                "initiative_count": 0,
                "research_group_count": 1,
                "advisorship_count": 0,
                "relation_types": [
                    "research_group"
                ],
                "source": 5268,
                "target": 5270
            },
            {
                "weight": 1,
                "initiative_count": 0,
                "research_group_count": 1,
                "advisorship_count": 0,
                "relation_types": [
                    "research_group"
                ],
                "source": 5268,
                "target": 5271
            },
            {
                "weight": 1,
                "initiative_count": 0,
                "research_group_count": 1,
                "advisorship_count": 0,
                "relation_types": [
                    "research_group"
                ],
                "source": 5268,
                "target": 5272
            },
            {
                "weight": 1,
                "initiative_count": 0,
                "research_group_count": 1,
                "advisorship_count": 0,
                "relation_types": [
                    "research_group"
                ],
                "source": 5268,
                "target": 5273
            },
            {
                "weight": 2,
                "initiative_count": 0,
                "research_group_count": 2,
                "advisorship_count": 0,
                "relation_types": [
                    "research_group"
                ],
                "source": 5268,
                "target": 5274
            },
            {
                "weight": 1,
                "initiative_count": 0,
                "research_group_count": 1,
                "advisorship_count": 0,
                "relation_types": [
                    "research_group"
                ],
                "source": 5268,
                "target": 5275
            },
            {
                "weight": 1,
                "initiative_count": 0,
                "research_group_count": 1,
                "advisorship_count": 0,
                "relation_types": [
                    "research_group"
                ],
                "source": 5268,
                "target": 5276
            },
            {
                "weight": 1,
                "initiative_count": 0,
                "research_group_count": 1,
                "advisorship_count": 0,
                "relation_types": [
                    "research_group"
                ],
                "source": 5268,
                "target": 5277
            },
            {
                "weight": 1,
                "initiative_count": 0,
                "research_group_count": 1,
                "advisorship_count": 0,
                "relation_types": [
                    "research_group"
                ],
                "source": 5268,
                "target": 5278
            },
            {
                "weight": 1,
                "initiative_count": 0,
                "research_group_count": 1,
                "advisorship_count": 0,
                "relation_types": [
                    "research_group"
                ],
                "source": 5268,
                "target": 5279
            },
            {
                "weight": 1,
                "initiative_count": 0,
                "research_group_count": 1,
                "advisorship_count": 0,
                "relation_types": [
                    "research_group"
                ],
                "source": 5269,
                "target": 238
            },
            {
                "weight": 1,
                "initiative_count": 0,
                "research_group_count": 1,
                "advisorship_count": 0,
                "relation_types": [
                    "research_group"
                ],
                "source": 5269,
                "target": 240
            },
            {
                "weight": 1,
                "initiative_count": 0,
                "research_group_count": 1,
                "advisorship_count": 0,
                "relation_types": [
                    "research_group"
                ],
                "source": 5269,
                "target": 5270
            },
            {
                "weight": 1,
                "initiative_count": 0,
                "research_group_count": 1,
                "advisorship_count": 0,
                "relation_types": [
                    "research_group"
                ],
                "source": 5269,
                "target": 5271
            },
            {
                "weight": 1,
                "initiative_count": 0,
                "research_group_count": 1,
                "advisorship_count": 0,
                "relation_types": [
                    "research_group"
                ],
                "source": 5269,
                "target": 5272
            },
            {
                "weight": 1,
                "initiative_count": 0,
                "research_group_count": 1,
                "advisorship_count": 0,
                "relation_types": [
                    "research_group"
                ],
                "source": 5269,
                "target": 5273
            },
            {
                "weight": 1,
                "initiative_count": 0,
                "research_group_count": 1,
                "advisorship_count": 0,
                "relation_types": [
                    "research_group"
                ],
                "source": 5269,
                "target": 5274
            },
            {
                "weight": 1,
                "initiative_count": 0,
                "research_group_count": 1,
                "advisorship_count": 0,
                "relation_types": [
                    "research_group"
                ],
                "source": 5269,
                "target": 5275
            },
            {
                "weight": 1,
                "initiative_count": 0,
                "research_group_count": 1,
                "advisorship_count": 0,
                "relation_types": [
                    "research_group"
                ],
                "source": 5269,
                "target": 5276
            },
            {
                "weight": 1,
                "initiative_count": 0,
                "research_group_count": 1,
                "advisorship_count": 0,
                "relation_types": [
                    "research_group"
                ],
                "source": 5269,
                "target": 5277
            },
            {
                "weight": 1,
                "initiative_count": 0,
                "research_group_count": 1,
                "advisorship_count": 0,
                "relation_types": [
                    "research_group"
                ],
                "source": 5269,
                "target": 5278
            },
            {
                "weight": 1,
                "initiative_count": 0,
                "research_group_count": 1,
                "advisorship_count": 0,
                "relation_types": [
                    "research_group"
                ],
                "source": 5269,
                "target": 5279
            },
            {
                "weight": 2,
                "initiative_count": 0,
                "research_group_count": 2,
                "advisorship_count": 0,
                "relation_types": [
                    "research_group"
                ],
                "source": 5270,
                "target": 238
            },
            {
                "weight": 2,
                "initiative_count": 0,
                "research_group_count": 2,
                "advisorship_count": 0,
                "relation_types": [
                    "research_group"
                ],
                "source": 5270,
                "target": 240
            },
            {
                "weight": 1,
                "initiative_count": 0,
                "research_group_count": 1,
                "advisorship_count": 0,
                "relation_types": [
                    "research_group"
                ],
                "source": 5270,
                "target": 5271
            },
            {
                "weight": 2,
                "initiative_count": 0,
                "research_group_count": 2,
                "advisorship_count": 0,
                "relation_types": [
                    "research_group"
                ],
                "source": 5270,
                "target": 5272
            },
            {
                "weight": 1,
                "initiative_count": 0,
                "research_group_count": 1,
                "advisorship_count": 0,
                "relation_types": [
                    "research_group"
                ],
                "source": 5270,
                "target": 5273
            },
            {
                "weight": 1,
                "initiative_count": 0,
                "research_group_count": 1,
                "advisorship_count": 0,
                "relation_types": [
                    "research_group"
                ],
                "source": 5270,
                "target": 5274
            },
            {
                "weight": 2,
                "initiative_count": 0,
                "research_group_count": 2,
                "advisorship_count": 0,
                "relation_types": [
                    "research_group"
                ],
                "source": 5270,
                "target": 5275
            },
            {
                "weight": 1,
                "initiative_count": 0,
                "research_group_count": 1,
                "advisorship_count": 0,
                "relation_types": [
                    "research_group"
                ],
                "source": 5270,
                "target": 5276
            },
            {
                "weight": 1,
                "initiative_count": 0,
                "research_group_count": 1,
                "advisorship_count": 0,
                "relation_types": [
                    "research_group"
                ],
                "source": 5270,
                "target": 5277
            },
            {
                "weight": 2,
                "initiative_count": 0,
                "research_group_count": 2,
                "advisorship_count": 0,
                "relation_types": [
                    "research_group"
                ],
                "source": 5270,
                "target": 5278
            },
            {
                "weight": 1,
                "initiative_count": 0,
                "research_group_count": 1,
                "advisorship_count": 0,
                "relation_types": [
                    "research_group"
                ],
                "source": 5270,
                "target": 5279
            },
            {
                "weight": 1,
                "initiative_count": 0,
                "research_group_count": 1,
                "advisorship_count": 0,
                "relation_types": [
                    "research_group"
                ],
                "source": 5271,
                "target": 238
            },
            {
                "weight": 1,
                "initiative_count": 0,
                "research_group_count": 1,
                "advisorship_count": 0,
                "relation_types": [
                    "research_group"
                ],
                "source": 5271,
                "target": 240
            },
            {
                "weight": 1,
                "initiative_count": 0,
                "research_group_count": 1,
                "advisorship_count": 0,
                "relation_types": [
                    "research_group"
                ],
                "source": 5271,
                "target": 5272
            },
            {
                "weight": 1,
                "initiative_count": 0,
                "research_group_count": 1,
                "advisorship_count": 0,
                "relation_types": [
                    "research_group"
                ],
                "source": 5271,
                "target": 5273
            },
            {
                "weight": 1,
                "initiative_count": 0,
                "research_group_count": 1,
                "advisorship_count": 0,
                "relation_types": [
                    "research_group"
                ],
                "source": 5271,
                "target": 5274
            },
            {
                "weight": 1,
                "initiative_count": 0,
                "research_group_count": 1,
                "advisorship_count": 0,
                "relation_types": [
                    "research_group"
                ],
                "source": 5271,
                "target": 5275
            },
            {
                "weight": 1,
                "initiative_count": 0,
                "research_group_count": 1,
                "advisorship_count": 0,
                "relation_types": [
                    "research_group"
                ],
                "source": 5271,
                "target": 5276
            },
            {
                "weight": 1,
                "initiative_count": 0,
                "research_group_count": 1,
                "advisorship_count": 0,
                "relation_types": [
                    "research_group"
                ],
                "source": 5271,
                "target": 5277
            },
            {
                "weight": 1,
                "initiative_count": 0,
                "research_group_count": 1,
                "advisorship_count": 0,
                "relation_types": [
                    "research_group"
                ],
                "source": 5271,
                "target": 5278
            },
            {
                "weight": 1,
                "initiative_count": 0,
                "research_group_count": 1,
                "advisorship_count": 0,
                "relation_types": [
                    "research_group"
                ],
                "source": 5271,
                "target": 5279
            },
            {
                "weight": 2,
                "initiative_count": 1,
                "research_group_count": 0,
                "advisorship_count": 1,
                "relation_types": [
                    "initiative",
                    "advisorship"
                ],
                "source": 5272,
                "target": 127
            },
            {
                "weight": 2,
                "initiative_count": 0,
                "research_group_count": 2,
                "advisorship_count": 0,
                "relation_types": [
                    "research_group"
                ],
                "source": 5272,
                "target": 238
            },
            {
                "weight": 2,
                "initiative_count": 0,
                "research_group_count": 2,
                "advisorship_count": 0,
                "relation_types": [
                    "research_group"
                ],
                "source": 5272,
                "target": 240
            },
            {
                "weight": 1,
                "initiative_count": 0,
                "research_group_count": 1,
                "advisorship_count": 0,
                "relation_types": [
                    "research_group"
                ],
                "source": 5272,
                "target": 5273
            },
            {
                "weight": 1,
                "initiative_count": 0,
                "research_group_count": 1,
                "advisorship_count": 0,
                "relation_types": [
                    "research_group"
                ],
                "source": 5272,
                "target": 5274
            },
            {
                "weight": 2,
                "initiative_count": 0,
                "research_group_count": 2,
                "advisorship_count": 0,
                "relation_types": [
                    "research_group"
                ],
                "source": 5272,
                "target": 5275
            },
            {
                "weight": 1,
                "initiative_count": 0,
                "research_group_count": 1,
                "advisorship_count": 0,
                "relation_types": [
                    "research_group"
                ],
                "source": 5272,
                "target": 5276
            },
            {
                "weight": 1,
                "initiative_count": 0,
                "research_group_count": 1,
                "advisorship_count": 0,
                "relation_types": [
                    "research_group"
                ],
                "source": 5272,
                "target": 5277
            },
            {
                "weight": 2,
                "initiative_count": 0,
                "research_group_count": 2,
                "advisorship_count": 0,
                "relation_types": [
                    "research_group"
                ],
                "source": 5272,
                "target": 5278
            },
            {
                "weight": 1,
                "initiative_count": 0,
                "research_group_count": 1,
                "advisorship_count": 0,
                "relation_types": [
                    "research_group"
                ],
                "source": 5272,
                "target": 5279
            },
            {
                "weight": 1,
                "initiative_count": 0,
                "research_group_count": 1,
                "advisorship_count": 0,
                "relation_types": [
                    "research_group"
                ],
                "source": 5273,
                "target": 238
            },
            {
                "weight": 1,
                "initiative_count": 0,
                "research_group_count": 1,
                "advisorship_count": 0,
                "relation_types": [
                    "research_group"
                ],
                "source": 5273,
                "target": 240
            },
            {
                "weight": 1,
                "initiative_count": 0,
                "research_group_count": 1,
                "advisorship_count": 0,
                "relation_types": [
                    "research_group"
                ],
                "source": 5273,
                "target": 5274
            },
            {
                "weight": 1,
                "initiative_count": 0,
                "research_group_count": 1,
                "advisorship_count": 0,
                "relation_types": [
                    "research_group"
                ],
                "source": 5273,
                "target": 5275
            },
            {
                "weight": 1,
                "initiative_count": 0,
                "research_group_count": 1,
                "advisorship_count": 0,
                "relation_types": [
                    "research_group"
                ],
                "source": 5273,
                "target": 5276
            },
            {
                "weight": 1,
                "initiative_count": 0,
                "research_group_count": 1,
                "advisorship_count": 0,
                "relation_types": [
                    "research_group"
                ],
                "source": 5273,
                "target": 5277
            },
            {
                "weight": 1,
                "initiative_count": 0,
                "research_group_count": 1,
                "advisorship_count": 0,
                "relation_types": [
                    "research_group"
                ],
                "source": 5273,
                "target": 5278
            },
            {
                "weight": 1,
                "initiative_count": 0,
                "research_group_count": 1,
                "advisorship_count": 0,
                "relation_types": [
                    "research_group"
                ],
                "source": 5273,
                "target": 5279
            },
            {
                "weight": 1,
                "initiative_count": 0,
                "research_group_count": 1,
                "advisorship_count": 0,
                "relation_types": [
                    "research_group"
                ],
                "source": 5274,
                "target": 238
            },
            {
                "weight": 1,
                "initiative_count": 0,
                "research_group_count": 1,
                "advisorship_count": 0,
                "relation_types": [
                    "research_group"
                ],
                "source": 5274,
                "target": 240
            },
            {
                "weight": 1,
                "initiative_count": 0,
                "research_group_count": 1,
                "advisorship_count": 0,
                "relation_types": [
                    "research_group"
                ],
                "source": 5274,
                "target": 5275
            },
            {
                "weight": 1,
                "initiative_count": 0,
                "research_group_count": 1,
                "advisorship_count": 0,
                "relation_types": [
                    "research_group"
                ],
                "source": 5274,
                "target": 5276
            },
            {
                "weight": 1,
                "initiative_count": 0,
                "research_group_count": 1,
                "advisorship_count": 0,
                "relation_types": [
                    "research_group"
                ],
                "source": 5274,
                "target": 5277
            },
            {
                "weight": 1,
                "initiative_count": 0,
                "research_group_count": 1,
                "advisorship_count": 0,
                "relation_types": [
                    "research_group"
                ],
                "source": 5274,
                "target": 5278
            },
            {
                "weight": 1,
                "initiative_count": 0,
                "research_group_count": 1,
                "advisorship_count": 0,
                "relation_types": [
                    "research_group"
                ],
                "source": 5274,
                "target": 5279
            },
            {
                "weight": 2,
                "initiative_count": 0,
                "research_group_count": 2,
                "advisorship_count": 0,
                "relation_types": [
                    "research_group"
                ],
                "source": 5275,
                "target": 238
            },
            {
                "weight": 2,
                "initiative_count": 0,
                "research_group_count": 2,
                "advisorship_count": 0,
                "relation_types": [
                    "research_group"
                ],
                "source": 5275,
                "target": 240
            },
            {
                "weight": 1,
                "initiative_count": 0,
                "research_group_count": 1,
                "advisorship_count": 0,
                "relation_types": [
                    "research_group"
                ],
                "source": 5275,
                "target": 5276
            },
            {
                "weight": 1,
                "initiative_count": 0,
                "research_group_count": 1,
                "advisorship_count": 0,
                "relation_types": [
                    "research_group"
                ],
                "source": 5275,
                "target": 5277
            },
            {
                "weight": 2,
                "initiative_count": 0,
                "research_group_count": 2,
                "advisorship_count": 0,
                "relation_types": [
                    "research_group"
                ],
                "source": 5275,
                "target": 5278
            },
            {
                "weight": 1,
                "initiative_count": 0,
                "research_group_count": 1,
                "advisorship_count": 0,
                "relation_types": [
                    "research_group"
                ],
                "source": 5275,
                "target": 5279
            },
            {
                "weight": 1,
                "initiative_count": 0,
                "research_group_count": 1,
                "advisorship_count": 0,
                "relation_types": [
                    "research_group"
                ],
                "source": 5276,
                "target": 238
            },
            {
                "weight": 1,
                "initiative_count": 0,
                "research_group_count": 1,
                "advisorship_count": 0,
                "relation_types": [
                    "research_group"
                ],
                "source": 5276,
                "target": 240
            },
            {
                "weight": 1,
                "initiative_count": 0,
                "research_group_count": 1,
                "advisorship_count": 0,
                "relation_types": [
                    "research_group"
                ],
                "source": 5276,
                "target": 5277
            },
            {
                "weight": 1,
                "initiative_count": 0,
                "research_group_count": 1,
                "advisorship_count": 0,
                "relation_types": [
                    "research_group"
                ],
                "source": 5276,
                "target": 5278
            },
            {
                "weight": 1,
                "initiative_count": 0,
                "research_group_count": 1,
                "advisorship_count": 0,
                "relation_types": [
                    "research_group"
                ],
                "source": 5276,
                "target": 5279
            },
            {
                "weight": 1,
                "initiative_count": 0,
                "research_group_count": 1,
                "advisorship_count": 0,
                "relation_types": [
                    "research_group"
                ],
                "source": 5277,
                "target": 238
            },
            {
                "weight": 1,
                "initiative_count": 0,
                "research_group_count": 1,
                "advisorship_count": 0,
                "relation_types": [
                    "research_group"
                ],
                "source": 5277,
                "target": 240
            },
            {
                "weight": 1,
                "initiative_count": 0,
                "research_group_count": 1,
                "advisorship_count": 0,
                "relation_types": [
                    "research_group"
                ],
                "source": 5277,
                "target": 5278
            },
            {
                "weight": 1,
                "initiative_count": 0,
                "research_group_count": 1,
                "advisorship_count": 0,
                "relation_types": [
                    "research_group"
                ],
                "source": 5277,
                "target": 5279
            },
            {
                "weight": 2,
                "initiative_count": 0,
                "research_group_count": 2,
                "advisorship_count": 0,
                "relation_types": [
                    "research_group"
                ],
                "source": 5278,
                "target": 238
            },
            {
                "weight": 2,
                "initiative_count": 0,
                "research_group_count": 2,
                "advisorship_count": 0,
                "relation_types": [
                    "research_group"
                ],
                "source": 5278,
                "target": 240
            },
            {
                "weight": 1,
                "initiative_count": 0,
                "research_group_count": 1,
                "advisorship_count": 0,
                "relation_types": [
                    "research_group"
                ],
                "source": 5278,
                "target": 5279
            },
            {
                "weight": 1,
                "initiative_count": 0,
                "research_group_count": 1,
                "advisorship_count": 0,
                "relation_types": [
                    "research_group"
                ],
                "source": 5279,
                "target": 238
            },
            {
                "weight": 1,
                "initiative_count": 0,
                "research_group_count": 1,
                "advisorship_count": 0,
                "relation_types": [
                    "research_group"
                ],
                "source": 5279,
                "target": 240
            },
            {
                "weight": 2,
                "initiative_count": 0,
                "research_group_count": 2,
                "advisorship_count": 0,
                "relation_types": [
                    "research_group"
                ],
                "source": 238,
                "target": 240
            }
        ]
    }
}